dist/mailbagit/_internal/certifi/py.typed
dist/mailbagit/_internal/lark/py.typed
mailbagit/__init__.py
mailbagit/controller.py
mailbagit/derivative.py
mailbagit/email_account.py
mailbagit/globals.py
mailbagit/guided.py
mailbagit/loggerx.py
mailbagit/models.py
mailbagit/derivatives/eml.py
mailbagit/derivatives/example.py
mailbagit/derivatives/html.py
mailbagit/derivatives/mbox.py
mailbagit/derivatives/pdf.py
mailbagit/derivatives/pdf_chrome.py
mailbagit/derivatives/txt.py
mailbagit/derivatives/warc.py
mailbagit/formats/eml.py
mailbagit/formats/example.py
mailbagit/formats/mbox.py
mailbagit/formats/msg.py
mailbagit/formats/pst.py
mailbagit/helper/__init__.py
mailbagit/helper/common.py
mailbagit/helper/controller.py
mailbagit/helper/derivative.py
mailbagit/helper/format.py
mailbagit-0.7.4.dist-info/licenses/LICENSE
tests/__init__.py
tests/test_controller.py
tests/test_formats.py
mailbagit-0.7.4.dist-info/METADATA
mailbagit-0.7.4.dist-info/WHEEL
mailbagit-0.7.4.dist-info/entry_points.txt
mailbagit-0.7.4.dist-info/top_level.txt
mailbagit-0.7.4.dist-info/RECORD
