Metadata-Version: 2.4
Name: mailbagit
Version: 0.7.4
Summary: A tool for preserving email in multiple preservation formats.
Home-page: https://github.com/UAlbanyArchives/mailbag
Author: Gregory Wiedeman
Author-email: gwiedeman@albany.edu
Classifier: Programming Language :: Python :: 3
Classifier: License :: OSI Approved :: MIT License
Classifier: Operating System :: OS Independent
Requires-Python: >=3.9
License-File: LICENSE
Requires-Dist: bagit<2,>=1.8.1
Requires-Dist: beautifulsoup4<5,>=4.11.1
Requires-Dist: black<26,>=23.7
Requires-Dist: jsonmodels<=2.5.0,>=2.2
Requires-Dist: extract_msg>=0.42.0
Requires-Dist: structlog<22,>=21.1.0
Requires-Dist: packaging<25,>=21.0
Requires-Dist: python-json-logger<3,>=2.0.2
Requires-Dist: pyparsing<3,>=2.1.0
Requires-Dist: pytest<8,>=7.0.1
Requires-Dist: python-dotenv<=0.19.1,>0.19.0
Requires-Dist: chardet<5,>=4.0.0
Requires-Dist: warcio<2,>=1.7.4
Requires-Dist: requests<3,>=2.27.1
Requires-Dist: cssutils<3,>=2.4.2
Requires-Dist: python-json-logger<3,>=2.0.2
Provides-Extra: gui
Requires-Dist: gooey<2,>=1.0.8.1; extra == "gui"
Provides-Extra: pst
Requires-Dist: libpff-python==20231205; extra == "pst"
Provides-Extra: dev
Requires-Dist: pyinstaller<6,==5.0.1; extra == "dev"
Dynamic: author
Dynamic: author-email
Dynamic: classifier
Dynamic: description
Dynamic: description-content-type
Dynamic: home-page
Dynamic: license-file
Dynamic: provides-extra
Dynamic: requires-dist
Dynamic: requires-python
Dynamic: summary
